airflow/providers/cncf/kubernetes/__init__.py
airflow/providers/cncf/kubernetes/example_dags/__init__.py
airflow/providers/cncf/kubernetes/example_dags/example_spark_kubernetes.py
airflow/providers/cncf/kubernetes/hooks/__init__.py
airflow/providers/cncf/kubernetes/hooks/kubernetes.py
airflow/providers/cncf/kubernetes/operators/__init__.py
airflow/providers/cncf/kubernetes/operators/kubernetes_pod.py
airflow/providers/cncf/kubernetes/operators/spark_kubernetes.py
airflow/providers/cncf/kubernetes/sensors/__init__.py
airflow/providers/cncf/kubernetes/sensors/spark_kubernetes.py
turbaszek_airflow_cncf_testcncf_kubernetes-0.0.0.dist-info/LICENSE
turbaszek_airflow_cncf_testcncf_kubernetes-0.0.0.dist-info/LICENSE-bootstrap-toggle.txt
turbaszek_airflow_cncf_testcncf_kubernetes-0.0.0.dist-info/LICENSE-bootstrap.txt
turbaszek_airflow_cncf_testcncf_kubernetes-0.0.0.dist-info/LICENSE-bootstrap3-typeahead.txt
turbaszek_airflow_cncf_testcncf_kubernetes-0.0.0.dist-info/LICENSE-d3-tip.txt
turbaszek_airflow_cncf_testcncf_kubernetes-0.0.0.dist-info/LICENSE-d3js.txt
turbaszek_airflow_cncf_testcncf_kubernetes-0.0.0.dist-info/LICENSE-dagre-d3.txt
turbaszek_airflow_cncf_testcncf_kubernetes-0.0.0.dist-info/LICENSE-datatables.txt
turbaszek_airflow_cncf_testcncf_kubernetes-0.0.0.dist-info/LICENSE-elasticmock.txt
turbaszek_airflow_cncf_testcncf_kubernetes-0.0.0.dist-info/LICENSE-eonasdan-bootstrap-datetimepicker.txt
turbaszek_airflow_cncf_testcncf_kubernetes-0.0.0.dist-info/LICENSE-flask-kerberos.txt
turbaszek_airflow_cncf_testcncf_kubernetes-0.0.0.dist-info/LICENSE-hue.txt
turbaszek_airflow_cncf_testcncf_kubernetes-0.0.0.dist-info/LICENSE-jqclock.txt
turbaszek_airflow_cncf_testcncf_kubernetes-0.0.0.dist-info/LICENSE-jquery.txt
turbaszek_airflow_cncf_testcncf_kubernetes-0.0.0.dist-info/LICENSE-moment-strftime.txt
turbaszek_airflow_cncf_testcncf_kubernetes-0.0.0.dist-info/LICENSE-moment.txt
turbaszek_airflow_cncf_testcncf_kubernetes-0.0.0.dist-info/LICENSE-normalize.txt
turbaszek_airflow_cncf_testcncf_kubernetes-0.0.0.dist-info/LICENSE-python-nvd3.txt
turbaszek_airflow_cncf_testcncf_kubernetes-0.0.0.dist-info/LICENSE-python-slugify.txt
turbaszek_airflow_cncf_testcncf_kubernetes-0.0.0.dist-info/METADATA
turbaszek_airflow_cncf_testcncf_kubernetes-0.0.0.dist-info/NOTICE
turbaszek_airflow_cncf_testcncf_kubernetes-0.0.0.dist-info/WHEEL
turbaszek_airflow_cncf_testcncf_kubernetes-0.0.0.dist-info/top_level.txt
turbaszek_airflow_cncf_testcncf_kubernetes-0.0.0.dist-info/RECORD
